coinlore/__init__.py
coinlore/client.py
coinlore-0.1.6.dist-info/LICENSE
coinlore-0.1.6.dist-info/METADATA
coinlore-0.1.6.dist-info/WHEEL
coinlore-0.1.6.dist-info/top_level.txt
coinlore-0.1.6.dist-info/RECORD
