Metadata-Version: 2.1
Name: coinlore
Version: 0.1.6
Summary: Coinlore cryptocurrency api https://www.coinlore.com
Home-page: https://github.com/coinlore/Python-Cryptocurrency-API-CoinLore
Author: CoinLore
Author-email: contact@coinlore.com
License: UNKNOWN
Keywords: api,coinlore,cryptocurrency,cryptocurrency prices,bitcoin,ethereum,XRP
Platform: UNKNOWN
Classifier: Programming Language :: Python :: 3
Classifier: License :: OSI Approved :: MIT License
Classifier: Operating System :: OS Independent
Requires-Dist: requests
